athenautility/__init__.py
athenautility/athena_client.py
athenautility/athena_loader.py
athenautility-1.5.2.dist-info/METADATA
athenautility-1.5.2.dist-info/WHEEL
athenautility-1.5.2.dist-info/top_level.txt
athenautility-1.5.2.dist-info/RECORD
